imageplustxt/__init__.py
imageplustxt/fonts/LDFComicSans.ttf
imageplustxt/fonts/LDFComicSansBold.ttf
imageplustxt/fonts/LDFComicSansHairline.ttf
imageplustxt/fonts/LDFComicSansLight.ttf
imageplustxt/fonts/arial.ttf
imageplustxt-0.1.4.dist-info/entry_points.txt
imageplustxt-0.1.4.dist-info/LICENSE
imageplustxt-0.1.4.dist-info/WHEEL
imageplustxt-0.1.4.dist-info/METADATA
imageplustxt-0.1.4.dist-info/RECORD
