Metadata-Version: 2.1
Name: imageplustxt
Version: 0.1.4
Summary: Module to add text to an image
Author-email: surumkata <a93277@uminho.pt>
Classifier: License :: OSI Approved :: MIT License
Requires-Dist: Pillow
Requires-Dist: argparse
